<?xml version='1.0' ?>
<!DOCTYPE libros SYSTEM "/home/horabaixa/LenguajeDeMarcas/libros/libros.dtd">

<libros>

	<libro isbn= "756" numcopia= "758">
		<titulo></titulo>
		<titulo></titulo>
		<autor></autor>
		<anyoedicion></anyoedicion>
		<numpaginas></numpaginas>
		<lengua>
			<espanyol></espanyol>
			<ingles></ingles>
			<frances></frances>
			<aleman></aleman>
		</lengua>
			
	</libro>
	<!--	
	<libro isbn= "" numcopia= "">
		<titulo></titulo>
		<titulo></titulo>	
		<autor></autor>
		<anyoedicion></anyoedicion>
		<numpaginas></numpaginas>
		<leng</lengua>
	</libro>	
	-->
</libros>